eo_validation/__init__.py
eo_validation/leafmap_dashboard.py
eo_validation/validation_dashboard.py
eo_validation-0.2.2.dist-info/LICENSE.md
eo_validation-0.2.2.dist-info/METADATA
eo_validation-0.2.2.dist-info/WHEEL
eo_validation-0.2.2.dist-info/top_level.txt
eo_validation-0.2.2.dist-info/zip-safe
eo_validation-0.2.2.dist-info/RECORD
