Metadata-Version: 2.1
Name: eo-validation
Version: 0.2.2
Summary: Collaborative validation tools for remote sensing imagery
Home-page: https://github.com/nasa-nccs-hpda/eo-validation
Author: Jordan A. Caraballo-Vega
Author-email: jordan.a.caraballo-vega@nasa.gov
License: BSD 3-Clause License
Keywords: validation,rioxarray,rasterio
Classifier: License :: OSI Approved :: BSD License
Classifier: Programming Language :: Python :: 3
License-File: LICENSE.md
Requires-Dist: geopandas
Requires-Dist: rioxarray
Requires-Dist: xarray
Requires-Dist: rasterio
Requires-Dist: pandas
Requires-Dist: numpy
Requires-Dist: tqdm
Requires-Dist: localtileserver
